{"swagger":"2.0","info":{"description":"测试","version":"v1","title":"K-Api"},"host":"192.168.3.233:8081","basePath":"","tags":[{"name":"测试标签","description":""}],"schemes":["http"],"paths":{"/api2/hello2/hello/list2":{"get":{"tags":["测试标签"],"summary":"","description":"","consumes":["application/json"],"produces":["application/json"],"parameters":[{"in":"query","name":"page","description":"页码","required":false,"type":"integer"},{"in":"query","name":"size","description":"页数量","required":false,"type":"integer"}],"responses":{"400":{"description":"参数错误"},"401":{"description":"鉴权失败"},"500":{"description":"操作失败"}}}},"/api2/hello2/list":{"get":{"tags":["测试标签"],"summary":"","description":"","consumes":["application/json"],"produces":["application/json"],"parameters":[{"in":"query","name":"page","description":"页码","required":false,"type":"integer"},{"in":"query","name":"size","description":"页数量","required":false,"type":"integer"}],"responses":{"400":{"description":"参数错误"},"401":{"description":"鉴权失败"},"500":{"description":"操作失败"}}}}},"securityDefinitions":{},"definitions":{"TestReq":{"type":"object","properties":{"page":{"type":"integer","format":"int","description":"页码"},"size":{"type":"integer","format":"int","description":"页数量"}},"xml":{"name":"","wrapped":false}}},"externalDocs":{}}